common/__init__.py
common/base/__init__.py
common/base/genor.py
common/base/input_listener.py
common/base/logger.py
common/base/mapper.py
common/base/multi_task.py
common/base/packer.py
common/base/registry.py
common/ext/__init__.py
common/ext/cookie_parser.py
common/ext/iphone_client.py
common/ext/qq_email.py
common/postman/__init__.py
common/postman/postman_api.py
common/postman/postman_impl.py
common/postman/postman_proxy.py
common/util/__init__.py
common/util/args_util.py
common/util/assert_util.py
common/util/decorator_util.py
common/util/file_util.py
common/util/image_util.py
common/util/json_util.py
common/util/requests_util.py
common/util/sys_util.py
common/util/time_util.py
common/util/typing_util.py
commonx-0.6.38.dist-info/METADATA
commonx-0.6.38.dist-info/WHEEL
commonx-0.6.38.dist-info/top_level.txt
commonx-0.6.38.dist-info/RECORD
